onemrigaka/__init__.py
onemrigaka/hellomri.py
onemrigaka/xtimes.py
onemrigaka/games/SnakeGame.py
onemrigaka/games/__init__.py
onemriganka-0.0.3.dist-info/LICENSE.txt
onemriganka-0.0.3.dist-info/METADATA
onemriganka-0.0.3.dist-info/WHEEL
onemriganka-0.0.3.dist-info/top_level.txt
onemriganka-0.0.3.dist-info/RECORD
