Metadata-Version: 2.1
Name: onemriganka
Version: 0.0.3
Summary: onemrigaka
Author: onemriganka
Keywords: onemriganka
Classifier: Development Status :: 1 - Planning
Classifier: Intended Audience :: Developers
Classifier: Programming Language :: Python :: 3
Classifier: Operating System :: Unix
Classifier: Operating System :: MacOS :: MacOS X
Classifier: Operating System :: Microsoft :: Windows
License-File: LICENSE.txt
Requires-Dist: PyAutoGUI
Requires-Dist: pygame
